pycounts_amm/__init__.py
pycounts_amm/plotting.py
pycounts_amm/pycounts_amm.py
pycounts_amm-0.1.0.dist-info/LICENSE
pycounts_amm-0.1.0.dist-info/WHEEL
pycounts_amm-0.1.0.dist-info/METADATA
pycounts_amm-0.1.0.dist-info/RECORD
