Metadata-Version: 2.1
Name: pycounts-amm
Version: 0.1.0
Summary: This package consists of a function that can be used to count the number of words in a text file.
License: MIT
Author: Abdul Moid Mohammed
Requires-Python: >=3.9,<4.0
Classifier: License :: OSI Approved :: MIT License
Classifier: Programming Language :: Python :: 3
Classifier: Programming Language :: Python :: 3.9
Requires-Dist: matplotlib (>=3.5.1,<4.0.0)
